{
    "version": "2.0.14",
    "homepage": "https://www.seafile.com",
    "description": "Exposes Seafile servers as Windows network drives.",
    "shortcuts": [
        [
            "Pfiles/SeaDrive/bin/seadrive-gui.exe",
            "SeaDrive"
        ]
    ],
    "checkver": {
        "url": "https://www.seafile.com/en/download/",
        "regex": "(?<url>https:\\/\\/[^\"]*seadrive-(?<version>\\d+\\.\\d+\\.\\d+)-en\\.msi)"
    },
    "url": "https://s3.eu-central-1.amazonaws.com/download.seadrive.org/seadrive-2.0.14-en.msi",
    "hash": "61f8fc1fd6eafe0af9feda401730735fe90bce98c2fc7bf6f2fdd680451ef3ba",
    "autoupdate": {
        "url": "$matchUrl"
    },
    "license": "Proprietary"
}
